behavex_images/__init__.py
behavex_images/extend_environment.py
behavex_images/image_attachments.py
behavex_images/img/html_test_report.png
behavex_images/img/html_test_report_2.png
behavex_images/img/html_test_report_3.png
behavex_images/utils/__init__.py
behavex_images/utils/image_format.py
behavex_images/utils/image_hash.py
behavex_images/utils/report_utils.py
behavex_images/utils/support_files/__init__.py
behavex_images/utils/support_files/behavex.css
behavex_images/utils/support_files/chart.js
behavex_images/utils/support_files/img_close.png
behavex_images/utils/support_files/img_loading.gif
behavex_images/utils/support_files/img_next.png
behavex_images/utils/support_files/img_prev.png
behavex_images/utils/support_files/jquery-1.11.0.min.js
behavex_images/utils/support_files/lightbox.css
behavex_images/utils/support_files/lightbox.js
behavex_images-3.3.1.dist-info/licenses/LICENSE
behavex_images-3.3.1.dist-info/METADATA
behavex_images-3.3.1.dist-info/WHEEL
behavex_images-3.3.1.dist-info/top_level.txt
behavex_images-3.3.1.dist-info/RECORD
