Metadata-Version: 2.4
Name: behavex-images
Version: 3.3.1
Summary: BehaveX extension library to attach images to the test execution report.
Author-email: Hernan Rey <hernanrey@gmail.com>, Ana Mercado <abmercado19@gmail.com>
License: MIT
Project-URL: Homepage, https://github.com/abmercado19/behavex-images
Project-URL: Repository, https://github.com/abmercado19/behavex-images
Project-URL: Issues, https://github.com/abmercado19/behavex-images/issues
Classifier: Development Status :: 5 - Production/Stable
Classifier: Environment :: Console
Classifier: Intended Audience :: Developers
Classifier: License :: OSI Approved :: MIT License
Classifier: Operating System :: OS Independent
Classifier: Programming Language :: Python
Classifier: Programming Language :: Python :: 3
Classifier: Programming Language :: Python :: 3.8
Classifier: Programming Language :: Python :: 3.9
Classifier: Programming Language :: Python :: 3.10
Classifier: Programming Language :: Python :: 3.11
Classifier: Programming Language :: Python :: 3.12
Classifier: Programming Language :: Python :: 3.13
Classifier: Topic :: Software Development :: Testing
Requires-Python: >=3.8
License-File: LICENSE
Requires-Dist: behavex
Requires-Dist: behave
Requires-Dist: pillow
Requires-Dist: filelock; python_version >= "3.8"
Dynamic: license-file
